{"dog": ["a [V] dog", "a [V] dog", "a [V] dog", "a [V] dog", "a [V] dog", "a [V] dog"], "cat": ["a [V] cat", "a [V] cat", "a [V] cat", "a [V] cat", "a [V] cat"], "glasses": ["a [V] glasses", "a [V] glasses", "a [V] glasses", "a [V] glasses", "a [V] glasses", "a [V] glasses"], "stuffed animal": ["a [V] stuffed animal", "a [V] stuffed animal", "a [V] stuffed animal", "a [V] stuffed animal", "a [V] stuffed animal"], "can": ["a [V] can", "a [V] can", "a [V] can", "a [V] can", "a [V] can", "a [V] can"], "toy": ["a [V] toy", "a [V] toy", "a [V] toy", "a [V] toy", "a [V] toy"], "boot": ["a [V] boot", "a [V] boot", "a [V] boot", "a [V] boot", "a [V] boot", "a [V] boot"], "bowl": ["a [V] bowl", "a [V] bowl", "a [V] bowl", "a [V] bowl", "a [V] bowl", "a [V] bowl"], "candle": ["a [V] candle", "a [V] candle", "a [V] candle", "a [V] candle", "a [V] candle"], "vase": ["a [V] vase", "a [V] vase", "a [V] vase", "a [V] vase", "a [V] vase", "a [V] vase"], "backpack": ["a [V] backpack", "a [V] backpack", "a [V] backpack", "a [V] backpack", "a [V] backpack"], "sneaker": ["a [V] sneaker", "a [V] sneaker", "a [V] sneaker", "a [V] sneaker", "a [V] sneaker"], "teapot": ["a [V] teapot", "a [V] teapot", "a [V] teapot", "a [V] teapot", "a [V] teapot"], "clock": ["a [V] clock", "a [V] clock", "a [V] clock", "a [V] clock", "a [V] clock", "a [V] clock"], "cartoon": ["a [V] cartoon", "a [V] cartoon", "a [V] cartoon", "a [V] cartoon"]}